ManufaiUnityTesting/__init__.py
ManufaiUnityTesting-0.0.1.dist-info/LICENCE.txt
ManufaiUnityTesting-0.0.1.dist-info/METADATA
ManufaiUnityTesting-0.0.1.dist-info/WHEEL
ManufaiUnityTesting-0.0.1.dist-info/top_level.txt
ManufaiUnityTesting-0.0.1.dist-info/RECORD
