Metadata-Version: 2.1
Name: ManufaiUnityTesting
Version: 0.0.1
Summary: Union de proyectos anteriores
Home-page: UNKNOWN
Author: Ari Bautista
Author-email: aribautista66@gmail.com
License: MIT
Keywords: Multiple Scripts For Dongle
Platform: UNKNOWN
Classifier: Development Status :: 5 - Production/Stable
Classifier: Intended Audience :: Education
Classifier: Operating System :: Microsoft :: Windows :: Windows 10
Classifier: License :: OSI Approved :: MIT License
Classifier: Programming Language :: Python :: 3
